celery_growthmonitor/__init__.py
celery_growthmonitor/admin.py
celery_growthmonitor/apps.py
celery_growthmonitor/canvas.py
celery_growthmonitor/forms.py
celery_growthmonitor/settings.py
celery_growthmonitor/tasks.py
celery_growthmonitor/models/__init__.py
celery_growthmonitor/models/job.py
celery_growthmonitor/models/jobholder.py
celery_growthmonitor/models/task.py
django_celery_growthmonitor-1.1.0.dist-info/LICENSE
django_celery_growthmonitor-1.1.0.dist-info/METADATA
django_celery_growthmonitor-1.1.0.dist-info/WHEEL
django_celery_growthmonitor-1.1.0.dist-info/top_level.txt
django_celery_growthmonitor-1.1.0.dist-info/RECORD
