Metadata-Version: 2.1
Name: django-celery-growthmonitor
Version: 1.1.0
Summary: A Django helper to monitor jobs running Celery tasks
Home-page: https://github.com/mbourqui/django-celery-growthmonitor/
Author: Marc Bourqui
Author-email: pypi.kemar@bourqui.org
License: GNU GPLv3
Download-URL: https://github.com/mbourqui/django-celery-growthmonitor/releases/tag/v1.1.0
Keywords: django utility celery celery-tasks monitoring
Platform: UNKNOWN
Classifier: Development Status :: 5 - Production/Stable
Classifier: Environment :: Web Environment
Classifier: Framework :: Django
Classifier: Framework :: Django :: 2.2
Classifier: Framework :: Django :: 3.2
Classifier: Intended Audience :: Developers
Classifier: License :: OSI Approved :: GNU General Public License v3 (GPLv3)
Classifier: Operating System :: OS Independent
Classifier: Programming Language :: Python
Classifier: Programming Language :: Python :: 3
Classifier: Programming Language :: Python :: 3.5
Classifier: Programming Language :: Python :: 3.6
Classifier: Programming Language :: Python :: 3.7
Classifier: Programming Language :: Python :: 3.8
Classifier: Programming Language :: Python :: 3.9
Classifier: Topic :: Internet :: WWW/HTTP
Classifier: Topic :: Internet :: WWW/HTTP :: Dynamic Content
Classifier: Topic :: Utilities
License-File: LICENSE
Requires-Dist: Django (>=2.2)
Requires-Dist: django-echoices (>=2.6.0)
Requires-Dist: celery (>=4.0.2)
Requires-Dist: django-autoslug (>=1.9.4)
